nodeconfig/__init__.py
nodeconfig/exceptionlogger.py
nodeconfig/exechelper.py
nodeconfig/fileupdater.py
nodeconfig/servicemanager.py
towalink_nodeconfig-0.1.2.dist-info/LICENSE
towalink_nodeconfig-0.1.2.dist-info/METADATA
towalink_nodeconfig-0.1.2.dist-info/WHEEL
towalink_nodeconfig-0.1.2.dist-info/entry_points.txt
towalink_nodeconfig-0.1.2.dist-info/top_level.txt
towalink_nodeconfig-0.1.2.dist-info/RECORD
