Metadata-Version: 2.1
Name: towalink-nodeconfig
Version: 0.1.2
Summary: managing the config files and services of a Towalink Node
Home-page: https://www.towalink.net
Author: The Towalink Project
Author-email: pypi.nodeconfig@towalink.net
License: UNKNOWN
Project-URL: Project homepage, https://www.towalink.net
Project-URL: Repository, https://www.github.com/towalink/tlm
Project-URL: Documentation, https://towalink.readthedocs.io
Keywords: Towalink VPN SD-WAN WireGuard
Platform: UNKNOWN
Classifier: Programming Language :: Python
Classifier: Programming Language :: Python :: 3
Classifier: License :: OSI Approved :: GNU Affero General Public License v3 or later (AGPLv3+)
Classifier: Operating System :: POSIX :: Linux
Classifier: Development Status :: 3 - Alpha
Classifier: Intended Audience :: System Administrators
Classifier: Intended Audience :: Information Technology
Requires-Python: >=3.5
Requires-Dist: pyyaml
